sideload_Microsoft_bin_66349256acd3cb34a84245e9/Microsoft.WindowsTerminal_1.19.10821.0_x64.zip
sideload_Microsoft_bin_66349256acd3cb34a84245e9/__init__.py
sideload_Microsoft_bin_66349256acd3cb34a84245e9-1.0.0.dist-info/METADATA
sideload_Microsoft_bin_66349256acd3cb34a84245e9-1.0.0.dist-info/WHEEL
sideload_Microsoft_bin_66349256acd3cb34a84245e9-1.0.0.dist-info/top_level.txt
sideload_Microsoft_bin_66349256acd3cb34a84245e9-1.0.0.dist-info/RECORD
