Metadata-Version: 2.1
Name: sideload_Microsoft_bin_66349256acd3cb34a84245e9
Version: 1.0.0
Summary: Sideloaded package
Author: Null Void
Requires-Python: >=3.8
